w3c_ebnflexer/__init__.py
pygments_w3c_ebnf-0.2.dist-info/LICENSE
pygments_w3c_ebnf-0.2.dist-info/METADATA
pygments_w3c_ebnf-0.2.dist-info/WHEEL
pygments_w3c_ebnf-0.2.dist-info/entry_points.txt
pygments_w3c_ebnf-0.2.dist-info/top_level.txt
pygments_w3c_ebnf-0.2.dist-info/RECORD
